litedao/__init__.py
litedao/__main__.py
litedao/pyrustic_data/backstage/config/build.json
litedao/pyrustic_data/backstage/config/init.json
litedao/pyrustic_data/backstage/config/release.json
litedao/pyrustic_data/backstage/data/build_report.json
litedao/pyrustic_data/backstage/data/github_release_form.json
litedao/pyrustic_data/backstage/hooking/build.json
litedao/pyrustic_data/backstage/hooking/init.json
litedao/pyrustic_data/backstage/hooking/release.json
litedao/pyrustic_data/backstage/report/build_report.json
litedao/pyrustic_data/backstage/report/release_report.json
litedao/pyrustic_data/hubstore/img.json
litedao/pyrustic_data/hubstore/promotion.json
tests/__init__.py
tests/__main__.py
litedao-0.0.7.dist-info/LICENSE
litedao-0.0.7.dist-info/METADATA
litedao-0.0.7.dist-info/WHEEL
litedao-0.0.7.dist-info/entry_points.txt
litedao-0.0.7.dist-info/top_level.txt
litedao-0.0.7.dist-info/RECORD
