Metadata-Version: 2.1
Name: litedao
Version: 0.0.7
Summary: Intuitive interaction with SQLite database
Home-page: https://github.com/pyrustic/litedao
Author: Pyrustic Evangelist
Author-email: rusticalex@yahoo.com
Maintainer: Pyrustic Evangelist
Maintainer-email: rusticalex@yahoo.com
License: MIT
Keywords: library,sqlite,sql,dao,database-access,pyrustic,lightweight
Platform: UNKNOWN
Classifier: Programming Language :: Python :: 3
Classifier: License :: OSI Approved :: MIT License
Classifier: Operating System :: OS Independent
Requires-Python: >=3.5
License-File: LICENSE
